trellostats/trellostats.py
trellostats/settings.py
trellostats/models.py
trellostats/cli.py
trellostats/__init__.py
trellostats-0.7.dist-info/RECORD
trellostats-0.7.dist-info/METADATA
trellostats-0.7.dist-info/WHEEL
trellostats-0.7.dist-info/metadata.json
trellostats-0.7.dist-info/entry_points.txt
trellostats-0.7.dist-info/top_level.txt
trellostats-0.7.dist-info/DESCRIPTION.rst
